{
	"name": "bronze",
	"properties": {
		"type": "MappingDataFlow",
		"typeProperties": {
			"sources": [
				{
					"dataset": {
						"referenceName": "dsBronzeSource",
						"type": "DatasetReference"
					},
					"name": "sourceBronze"
				}
			],
			"sinks": [
				{
					"dataset": {
						"referenceName": "ds_silver",
						"type": "DatasetReference"
					},
					"name": "SilverDestination"
				}
			],
			"transformations": [
				{
					"name": "filter1"
				},
				{
					"name": "addDomain"
				},
				{
					"name": "derivedColumn1"
				}
			],
			"scriptLines": [
				"source(output(",
				"          OrderID as string,",
				"          OrderDate as date,",
				"          CustomerID as string,",
				"          CustomerName as string,",
				"          CustomerEmail as string,",
				"          ProductID as string,",
				"          ProductName as string,",
				"          ProductCategory as string,",
				"          RegionID as string,",
				"          RegionName as string,",
				"          Country as string,",
				"          Quantity as integer,",
				"          UnitPrice as integer,",
				"          TotalAmount as integer",
				"     ),",
				"     allowSchemaDrift: true,",
				"     validateSchema: false,",
				"     ignoreNoFilesFound: false,",
				"     format: 'parquet') ~> sourceBronze",
				"sourceBronze filter(UnitPrice >=100) ~> filter1",
				"filter1 derive(Domain = split(CustomerEmail,'@')) ~> addDomain",
				"addDomain derive(Domain = slice(Domain,2)[1]) ~> derivedColumn1",
				"derivedColumn1 sink(allowSchemaDrift: true,",
				"     validateSchema: false,",
				"     format: 'parquet',",
				"     umask: 0022,",
				"     preCommands: [],",
				"     postCommands: [],",
				"     skipDuplicateMapInputs: true,",
				"     skipDuplicateMapOutputs: true) ~> SilverDestination"
			]
		}
	}
}